decision_tree/__init__.py
decision_tree/classification.py
decision_trees_rap-0.1.0.dist-info/METADATA
decision_trees_rap-0.1.0.dist-info/WHEEL
decision_trees_rap-0.1.0.dist-info/RECORD
